{
    "vaibhav": {
        "fullname": "Vaibhav Sonkusare",
        "username": "vaibhav",
        "email": "va@g.com",
        "password": "$2y$10$ydBvINTwtT4w9mvbMiJcku19RaeyyKvi7R.c0hT9LIZHeqqfteyOO"
    },
    "test": {
        "fullname": "Tafokdsl",
        "username": "test",
        "email": "t@g.com",
        "password": "$2y$10$iK\/sf5NiJizJQd7SwvxZIeQ2teW1S3\/r\/kkM3unBTkXY0P6P5BuJu"
    },
    "testt": {
        "fullname": "Vaibhav Sonkusare",
        "username": "testt",
        "email": "va@g.com",
        "password": "test"
    }
}